trytond_factories/__init__.py
trytond_factories/account.py
trytond_factories/action.py
trytond_factories/attachment.py
trytond_factories/company.py
trytond_factories/currency.py
trytond_factories/invoice.py
trytond_factories/party.py
trytond_factories/product.py
trytond_factories/purchase.py
trytond_factories/sale.py
trytond_factories/sale_amendment.py
trytond_factories/sequence.py
trytond_factories/stock.py
trytond_factories/test.py
trytond_factories/tools.py
trytond_factories/user.py
trytond_factories/wizards.py
trytond_factories-7.2.0.dist-info/LICENSE
trytond_factories-7.2.0.dist-info/METADATA
trytond_factories-7.2.0.dist-info/WHEEL
trytond_factories-7.2.0.dist-info/top_level.txt
trytond_factories-7.2.0.dist-info/RECORD
