Metadata-Version: 2.1
Name: trytond-factories
Version: 7.2.0
Summary: A collection of opinionated factories for common Tryton modules
Home-page: https://github.com/calidae/trytond-factories
Author: Calidae
Author-email: dev@calidae.com
License: GPLv3+
Platform: any
Classifier: Development Status :: 5 - Production/Stable
Classifier: Framework :: Tryton
Classifier: Intended Audience :: Developers
Classifier: License :: OSI Approved :: GNU General Public License v3 or later (GPLv3+)
Classifier: Operating System :: OS Independent
Classifier: Programming Language :: Python :: 3
Classifier: Programming Language :: Python :: 3 :: Only
Classifier: Programming Language :: Python :: 3.8
Classifier: Programming Language :: Python :: 3.9
Classifier: Programming Language :: Python :: 3.10
Classifier: Programming Language :: Python :: 3.11
Classifier: Topic :: Software Development :: Testing :: Unit
Requires-Python: >=3.8
License-File: LICENSE
Requires-Dist: factory-trytond
Requires-Dist: trytond ~=7.2.0
Provides-Extra: tests
Requires-Dist: pytest-trytond ; extra == 'tests'
Requires-Dist: trytond-account-invoice ~=7.2.0 ; extra == 'tests'
